pybutton/__init__.py
pybutton/client.py
pybutton/constants.py
pybutton/error.py
pybutton/request.py
pybutton/response.py
pybutton/utils.py
pybutton/version.py
pybutton/resources/__init__.py
pybutton/resources/accounts.py
pybutton/resources/customers.py
pybutton/resources/links.py
pybutton/resources/merchants.py
pybutton/resources/orders.py
pybutton/resources/resource.py
pybutton/resources/transactions.py
pybutton-3.0.0.dist-info/LICENSE
pybutton-3.0.0.dist-info/METADATA
pybutton-3.0.0.dist-info/WHEEL
pybutton-3.0.0.dist-info/top_level.txt
pybutton-3.0.0.dist-info/zip-safe
pybutton-3.0.0.dist-info/RECORD
